[
  {
    "accountId": 0,
    "cookie": "[vY.M-SnelUZ]z^uw=rhK8UmnZN7>_",
    "expiration": 1649742176.3276029
  },
  {
    "accountId": 1,
    "cookie": "C1NP8gD<r>.{hAda;R2K{17VNpWP15",
    "expiration": 1649770539.1430967
  },
  {
    "accountId": 0,
    "cookie": "6ibzO1|964O831TFx;U]^d>c.gD-LJ",
    "expiration": 1649775497.1451886
  },
  {
    "accountId": 0,
    "cookie": "Blj7X18aTM<>0pcgZ6TRi:XRWz|891",
    "expiration": 1649779877.9860325
  },
  {
    "accountId": 0,
    "cookie": "6TCdJK-TQFw{j.@Tj}R{4KRoqh/Y4`",
    "expiration": 1649952014.932629
  }
]